igdb/__init__.py
igdb/igdbapi_pb2.py
igdb/wrapper.py
igdb_api_v3-0.0.2.dist-info/LICENSE
igdb_api_v3-0.0.2.dist-info/METADATA
igdb_api_v3-0.0.2.dist-info/WHEEL
igdb_api_v3-0.0.2.dist-info/top_level.txt
igdb_api_v3-0.0.2.dist-info/RECORD
