Metadata-Version: 2.1
Name: igdb-api-v3
Version: 0.0.2
Summary: An API wrapper for IGDB API v3
Home-page: https://github.com/igdb/igdb-api-python/
Author: Felix Nordén
Author-email: felixnorden@gmail.com
License: UNKNOWN
Platform: UNKNOWN
Classifier: Programming Language :: Python :: 3
Classifier: License :: OSI Approved :: MIT License
Classifier: Operating System :: OS Independent
Requires-Python: >=3
Requires-Dist: requests
